pyimc-0.1.2.dist-info/METADATA
pyimc-0.1.2.dist-info/WHEEL
pyimc/__init__.py
pyimc/pyimc.cpython-38-x86_64-linux-gnu.so
pyimc-0.1.2.dist-info/RECORD
