Metadata-Version: 2.1
Name: pyimc
Version: 0.1.2
Home-Page: https://github.com/AlanRace/imc-rs
Author: Alan Race <alan.race@uni-marburg.de>
Author-email: Alan Race <alan.race@uni-marburg.de>
License: MIT
Project-URL: Source Code, https://github.com/AlanRace/imc-rs.git
